npf_compare.py
npf_run.py
npf_watch.py
modules/__init__.py
modules/cpufreq-script-half.npf
modules/cpufreq-script.npf
modules/cpufreq.npf
modules/cpuload.npf
modules/dev_channels.npf
modules/dev_irq_affinity.npf
modules/dev_pause.npf
modules/dev_rate.npf
modules/dpdk-bind.npf
modules/droptcpsock.npf
modules/fastclick-play-single-mt.npf
modules/fastclick-rcv.npf
modules/fastclick-replay-dual.npf
modules/fastclick-replay-quad.npf
modules/fastclick-replay-single-mt-rated.npf
modules/fastclick-replay-single-mt-timing.npf
modules/fastclick-replay-single-mt.npf
modules/fastclick-replay-single-multitrace-tmp.npf
modules/fastclick-replay-single-multitrace.npf
modules/fastclick-replay-single-pipeline.npf
modules/fastclick-replay-single.npf
modules/fastclick-replay-txonly-mt.npf
modules/fastclick-replay-vmdq-quad.npf
modules/fastclick-udpgen-dual.npf
modules/fastclick-udpgen-latency-dual.npf
modules/fastclick-udpgen-latency-quad.npf
modules/fastclick-udpgen-latency-single-multiclient.npf
modules/fastclick-udpgen-latency-single.npf
modules/fastclick-udpgen-quad.npf
modules/fastclick-udpgen-single.npf
modules/fastclick-udpgen-snd.npf
modules/graph-beautiful.npf
modules/load.npf
modules/load2.npf
modules/netmap-bind.npf
modules/nginx.npf
modules/perf-class.npf
modules/perf-functions.npf
modules/perf-stat.npf
modules/perf-stat_BACKUP_4093132.npf
modules/perf-stat_BASE_4093132.npf
modules/perf-stat_LOCAL_4093132.npf
modules/perf-stat_REMOTE_4093132.npf
modules/pktgen.npf
modules/reframer.npf
modules/snort.npf
modules/trex.npf
modules/tune.npf
modules/waitcon.npf
modules/wrk-multins.npf
modules/wrk-nsdelay.npf
modules/wrk.npf
modules/wrk2.npf
npf/__init__.py
npf/build.py
npf/eventbus.py
npf/grapher.py
npf/module.py
npf/nic.py
npf/node.py
npf/npf.py
npf/regression.py
npf/repository.py
npf/section.py
npf/statistics.py
npf/testie.py
npf/variable.py
npf/executor/__init__.py
npf/executor/executor.py
npf/executor/localexecutor.py
npf/executor/sshexecutor.py
npf/types/__init__.py
npf-1.0.42.dist-info/LICENSE
npf-1.0.42.dist-info/METADATA
npf-1.0.42.dist-info/WHEEL
npf-1.0.42.dist-info/entry_points.txt
npf-1.0.42.dist-info/top_level.txt
npf-1.0.42.dist-info/RECORD
