Metadata-Version: 2.1
Name: npf
Version: 1.0.42
Summary: NPF
Home-page: https://github.com/tbarbette/npf
Author: Tom Barbette
Author-email: t.barbette@gmail.com
Classifier: Programming Language :: Python :: 3
Classifier: License :: OSI Approved :: MIT License
Classifier: Operating System :: OS Independent
Requires-Python: >=3.6
License-File: LICENSE
Requires-Dist: require-python-3
Requires-Dist: pandas
Requires-Dist: numpy
Requires-Dist: regex
Requires-Dist: matplotlib
Requires-Dist: gitpython
Requires-Dist: typing
Requires-Dist: pydotplus
Requires-Dist: scipy
Requires-Dist: scikit-learn
Requires-Dist: paramiko
Requires-Dist: asteval
Requires-Dist: cryptography (==39.0.1)
Requires-Dist: gitdb
Requires-Dist: pyasn1
Requires-Dist: natsort
Requires-Dist: webcolors
Requires-Dist: colorama
Requires-Dist: pygtrie
Requires-Dist: packaging
Requires-Dist: importlib-metadata
Requires-Dist: orderedset ; python_version < "3.7.0"
Requires-Dist: ordered-set ; python_version >= "3.7.0"
